ptcompletion/__init__.py
ptcompletion/openai_task.py
ptcompletion/task.py
ptcompletion/task_queue.py
ptcompletion-0.2.1.dist-info/LICENSE
ptcompletion-0.2.1.dist-info/METADATA
ptcompletion-0.2.1.dist-info/WHEEL
ptcompletion-0.2.1.dist-info/top_level.txt
ptcompletion-0.2.1.dist-info/RECORD
