Metadata-Version: 2.1
Name: ptcompletion
Version: 0.2.1
Summary: Parallel Tasks Completion for OpenAI API, and more.
Home-page: https://github.com/Phantivia/OpenAI_PTCompletion
Author: Phantivia
Author-email: phantivia@gmail.com
Classifier: Development Status :: 3 - Alpha
Classifier: License :: OSI Approved :: MIT License
Classifier: Programming Language :: Python :: 3
Classifier: Programming Language :: Python :: 3.10
Requires-Python: >=3.10
License-File: LICENSE
Requires-Dist: openai
